ahmetx_loghero-1.0.0.dist-info/licenses/LICENSE
loghero/__init__.py
loghero/analyzer.py
loghero/cli.py
loghero/detectors.py
loghero/parsers.py
ahmetx_loghero-1.0.0.dist-info/METADATA
ahmetx_loghero-1.0.0.dist-info/WHEEL
ahmetx_loghero-1.0.0.dist-info/entry_points.txt
ahmetx_loghero-1.0.0.dist-info/top_level.txt
ahmetx_loghero-1.0.0.dist-info/RECORD
