Metadata-Version: 2.4
Name: AhmetX-LogHero
Version: 1.0.0
Summary: System log analyzer for detecting suspicious activities
Home-page: https://github.com/ahmetxhero/AhmetX-LogHero
Author: Ahmet KAHRAMAN (AhmetXHero)
Author-email: "Ahmet KAHRAMAN (AhmetXHero)" <ahmetxhero@gmail.com>
License: MIT
Project-URL: Homepage, https://github.com/ahmetxhero/AhmetX-LogHero
Project-URL: Bug Reports, https://github.com/ahmetxhero/AhmetX-LogHero/issues
Project-URL: Source, https://github.com/ahmetxhero/AhmetX-LogHero
Keywords: log,analysis,security,ssh,brute-force,system,administration
Classifier: Development Status :: 4 - Beta
Classifier: Intended Audience :: System Administrators
Classifier: License :: OSI Approved :: MIT License
Classifier: Operating System :: OS Independent
Classifier: Programming Language :: Python :: 3
Classifier: Programming Language :: Python :: 3.7
Classifier: Programming Language :: Python :: 3.8
Classifier: Programming Language :: Python :: 3.9
Classifier: Programming Language :: Python :: 3.10
Classifier: Programming Language :: Python :: 3.11
Classifier: Topic :: System :: Systems Administration
Classifier: Topic :: Security
Requires-Python: >=3.7
License-File: LICENSE
Requires-Dist: click>=8.0.0
Requires-Dist: colorama>=0.4.4
Requires-Dist: python-dateutil>=2.8.0
Requires-Dist: tabulate>=0.9.0
Dynamic: author
Dynamic: home-page
Dynamic: license-file
Dynamic: requires-python
